Metadata-Version: 1.1
Name: ScrapyElasticSearch
Version: 0.7.1
Summary: Scrapy pipeline which allow you to store multiple scrapy items in Elastic Search.
Home-page: https://github.com/knockrentals/scrapy-elasticsearch.git
Author: Michael Malocha, Julien Duponchelle
Author-email: michael@knockrentals.com, julien@duponchelle.info
License: Apache License, Version 2.0
Download-URL: https://github.com/knockrentals/scrapy-elasticsearch/tarball/master
Keywords: scrapy elastic search
Platform: Any
Classifier: Development Status :: 4 - Beta
Classifier: Environment :: No Input/Output (Daemon)
Classifier: License :: OSI Approved :: Apache Software License
Classifier: Operating System :: OS Independent
Classifier: Programming Language :: Python
